<?xml version="1.0" encoding="UTF-8" standalone="no"?>
<databaseChangeLog xmlns="http://www.liquibase.org/xml/ns/dbchangelog"
	xmlns:xsi="http://www.w3.org/2001/XMLSchema-instance"
	xsi:schemaLocation="http://www.liquibase.org/xml/ns/dbchangelog http://www.liquibase.org/xml/ns/dbchangelog/dbchangelog-2.0.xsd">
	<changeSet author="root (generated)" id="1343314492758-1">
		<preConditions onFail="MARK_RAN"
			onFailMessage="Table AUDIT_OPERATION already exists. Skipping creation of the table...">
			<not>
				<tableExists tableName="AUDIT_OPERATION" />
			</not>
		</preConditions>
		<createTable tableName="AUDIT_OPERATION">
			<column autoIncrement="true" name="ID" type="BIGINT">
				<constraints nullable="false" primaryKey="true" />
			</column>
			<column name="VERSION" type="INT" />
			<column name="INSTANT" type="DATETIME" />
			<column name="OPERATION" type="VARCHAR(255)" />
			<column name="VALUE" type="LONGTEXT" />
			<column name="KEY_AUDITED" type="BIGINT" />
			<column name="KEY_AUDITOR" type="BIGINT" />
		</createTable>
	</changeSet>
	<changeSet author="root (generated)" id="1343314492758-2">
		<preConditions onFail="MARK_RAN"
			onFailMessage="Table AUDITED_OBJECT already exists. Skipping creation of the table...">
			<not>
				<tableExists tableName="AUDITED_OBJECT" />
			</not>
		</preConditions>
		<createTable tableName="AUDITED_OBJECT">
			<column autoIncrement="true" name="ID" type="BIGINT">
				<constraints nullable="false" primaryKey="true" />
			</column>
			<column name="VERSION" type="INT" />
		</createTable>
	</changeSet>
	<changeSet author="root (generated)" id="1343314492758-3">
		<preConditions onFail="MARK_RAN"
			onFailMessage="Table AUDITOR already exists. Skipping creation of the table...">
			<not>
				<tableExists tableName="AUDITOR" />
			</not>
		</preConditions>
		<createTable tableName="AUDITOR">
			<column autoIncrement="true" name="ID" type="BIGINT">
				<constraints nullable="false" primaryKey="true" />
			</column>
			<column name="VERSION" type="INT" />
			<column name="GENERIC_OPERATION" type="VARCHAR(255)" />
			<column name="OPERATION_DATE" type="DATETIME" />
			<column name="PERFORMED_BY" type="VARCHAR(255)">
				<constraints nullable="false" />
			</column>
		</createTable>
	</changeSet>
	<changeSet author="root (generated)" id="1343314492758-4">
		<preConditions onFail="MARK_RAN"
			onFailMessage="Table BAD_WORD already exists. Skipping creation of the table...">
			<not>
				<tableExists tableName="BAD_WORD" />
			</not>
		</preConditions>
		<createTable tableName="BAD_WORD">
			<column autoIncrement="true" name="ID" type="BIGINT">
				<constraints nullable="false" primaryKey="true" />
			</column>
			<column name="VERSION" type="INT" />
			<column name="LOCALE" type="VARCHAR(20)" />
			<column name="REGEX" type="VARCHAR(254)" />
		</createTable>
	</changeSet>
	<changeSet author="root (generated)" id="1343314492758-5">
		<preConditions onFail="MARK_RAN"
			onFailMessage="Table CHANNEL_AQUISITION_CONFIG already exists. Skipping creation of the table...">
			<not>
				<tableExists tableName="CHANNEL_AQUISITION_CONFIG" />
			</not>
		</preConditions>
		<createTable tableName="CHANNEL_AQUISITION_CONFIG">
			<column autoIncrement="true" name="ID" type="BIGINT">
				<constraints nullable="false" primaryKey="true" />
			</column>
			<column name="VERSION" type="INT" />
			<column name="CHANNEL_NAME" type="VARCHAR(255)" />
			<column name="APPLIED_MULTIPLIER" type="VARCHAR(255)" />
			<column name="FREQUENCY" type="DOUBLE" />
			<column name="FREQUENCY_DEF_TYPE" type="VARCHAR(255)" />
			<column name="DATE" type="DATE" />
			<column name="HOURS" type="TINYINT" />
			<column name="MICROS" type="SMALLINT" />
			<column name="MILIS" type="SMALLINT" />
			<column name="MINUTES" type="TINYINT" />
			<column name="NANOS" type="SMALLINT" />
			<column name="PICOS" type="SMALLINT" />
			<column name="SECONDS" type="TINYINT" />
			<column name="TOTAL_SAMPLES" type="INT" />
			<column name="KEY_HARDWARE_ACQUISITION_CONFIG" type="BIGINT" />
			<column name="KEY_SCALE" type="BIGINT">
				<constraints nullable="false" />
			</column>
		</createTable>
	</changeSet>
	<changeSet author="root (generated)" id="1343314492758-6">
		<preConditions onFail="MARK_RAN"
			onFailMessage="Table DATA_PRODUCER already exists. Skipping creation of the table...">
			<not>
				<tableExists tableName="DATA_PRODUCER" />
			</not>
		</preConditions>
		<createTable tableName="DATA_PRODUCER">
			<column autoIncrement="true" name="ID" type="BIGINT">
				<constraints nullable="false" primaryKey="true" />
			</column>
			<column name="VERSION" type="INT" />
			<column name="DATA_COLLECTOR_STATE" type="VARCHAR(255)" />
			<column name="DATA_PRODUCER_NAME" type="VARCHAR(255)" />
			<column name="OID" type="VARCHAR(255)">
				<constraints nullable="false" />
			</column>
			<column name="USER" type="VARCHAR(255)" />
			<column name="KEY_HARDWARE_ACQUISITION_CONFIG" type="BIGINT">
				<constraints nullable="false" />
			</column>
			<column name="KEY_SAMPLES_PACKET_BLOB" type="BIGINT" />
		</createTable>
	</changeSet>
	<changeSet author="root (generated)" id="1343314492758-7">
		<preConditions onFail="MARK_RAN"
			onFailMessage="Table ERROR_MESSAGE already exists. Skipping creation of the table...">
			<not>
				<tableExists tableName="ERROR_MESSAGE" />
			</not>
		</preConditions>
		<createTable tableName="ERROR_MESSAGE">
			<column autoIncrement="true" name="ID" type="BIGINT">
				<constraints nullable="false" primaryKey="true" />
			</column>
			<column name="VERSION" type="INT" />
			<column name="CATEGORY" type="VARCHAR(255)" />
			<column name="DATE_OF_ERROR" type="DATETIME" />
			<column name="MESSAGE" type="VARCHAR(500)" />
		</createTable>
	</changeSet>
	<changeSet author="root (generated)" id="1343314492758-8">
		<preConditions onFail="MARK_RAN"
			onFailMessage="Table EXPERIMENT already exists. Skipping creation of the table...">
			<not>
				<tableExists tableName="EXPERIMENT" />
			</not>
		</preConditions>
		<createTable tableName="EXPERIMENT">
			<column autoIncrement="true" name="ID" type="BIGINT">
				<constraints nullable="false" primaryKey="true" />
			</column>
			<column name="VERSION" type="INT" />
			<column name="DESCRIPTION" type="VARCHAR(255)" />
			<column name="EXTERNAL_ID" type="VARCHAR(255)" />
			<column name="NAME" type="VARCHAR(255)" />
			<column name="IS_ACTIVE" type="BIT" />
			<column name="HELP_MESSAGE" type="VARCHAR(255)" />
			<column name="LABEL" type="VARCHAR(255)" />
			<column name="URL" type="VARCHAR(255)" />
			<column name="KEY_LABORATORY" type="BIGINT" />
		</createTable>
	</changeSet>
	<changeSet author="root (generated)" id="1343314492758-9">
		<preConditions onFail="MARK_RAN"
			onFailMessage="Table HARDWARE_ACQUISITION_CONFIG already exists. Skipping creation of the table...">
			<not>
				<tableExists tableName="HARDWARE_ACQUISITION_CONFIG" />
			</not>
		</preConditions>
		<createTable tableName="HARDWARE_ACQUISITION_CONFIG">
			<column autoIncrement="true" name="ID" type="BIGINT">
				<constraints nullable="false" primaryKey="true" />
			</column>
			<column name="VERSION" type="INT" />
			<column name="FAMILIAR_NAME" type="VARCHAR(255)" />
			<column name="APPLIED_MULTIPLIER" type="VARCHAR(255)" />
			<column name="FREQUENCY" type="DOUBLE" />
			<column name="FREQUENCY_DEF_TYPE" type="VARCHAR(255)" />
			<column name="HARDWARE_UNIQUE_ID" type="VARCHAR(255)" />
			<column name="DATE" type="DATE" />
			<column name="HOURS" type="TINYINT" />
			<column name="MICROS" type="SMALLINT" />
			<column name="MILIS" type="SMALLINT" />
			<column name="MINUTES" type="TINYINT" />
			<column name="NANOS" type="SMALLINT" />
			<column name="PICOS" type="SMALLINT" />
			<column name="SECONDS" type="TINYINT" />
			<column name="TOTAL_SAMPLES" type="INT" />
		</createTable>
	</changeSet>
	<changeSet author="root (generated)" id="1343314492758-10">
		<preConditions onFail="MARK_RAN"
			onFailMessage="Table IDENTIFICATION already exists. Skipping creation of the table...">
			<not>
				<tableExists tableName="IDENTIFICATION" />
			</not>
		</preConditions>
		<createTable tableName="IDENTIFICATION">
			<column name="INSTANCE_TYPE" type="VARCHAR(31)">
				<constraints nullable="false" />
			</column>
			<column autoIncrement="true" name="ID" type="BIGINT">
				<constraints nullable="false" primaryKey="true" />
			</column>
			<column name="VERSION" type="INT" />
			<column name="PASSWORD" type="VARCHAR(255)" />
			<column name="KEY_USER" type="BIGINT" />
		</createTable>
	</changeSet>
	<changeSet author="root (generated)" id="1343314492758-11">
		<preConditions onFail="MARK_RAN"
			onFailMessage="Table LABORATORY already exists. Skipping creation of the table...">
			<not>
				<tableExists tableName="LABORATORY" />
			</not>
		</preConditions>
		<createTable tableName="LABORATORY">
			<column autoIncrement="true" name="ID" type="BIGINT">
				<constraints nullable="false" primaryKey="true" />
			</column>
			<column name="VERSION" type="INT" />
			<column name="DESCRIPTION" type="VARCHAR(255)" />
			<column name="JMX_PASS" type="VARCHAR(255)" />
			<column name="JMX_URL" type="VARCHAR(255)" />
			<column name="JMX_USER" type="VARCHAR(255)" />
			<column name="NAME" type="VARCHAR(255)" />
			<column name="IS_ACTIVE" type="BIT" />
			<column name="HELP_MESSAGE" type="VARCHAR(255)" />
			<column name="LABEL" type="VARCHAR(255)" />
			<column name="URL" type="VARCHAR(255)" />
		</createTable>
	</changeSet>
	<changeSet author="root (generated)" id="1343314492758-12">
		<preConditions onFail="MARK_RAN"
			onFailMessage="Table LOGIN_DOMAIN already exists. Skipping creation of the table...">
			<not>
				<tableExists tableName="LOGIN_DOMAIN" />
			</not>
		</preConditions>
		<createTable tableName="LOGIN_DOMAIN">
			<column autoIncrement="true" name="ID" type="BIGINT">
				<constraints nullable="false" primaryKey="true" />
			</column>
			<column name="VERSION" type="INT" />
			<column name="NAME" type="VARCHAR(255)">
				<constraints nullable="false" />
			</column>
			<column name="URL" type="VARCHAR(255)" />
		</createTable>
	</changeSet>
	<changeSet author="root (generated)" id="1343314492758-13">
		<preConditions onFail="MARK_RAN"
			onFailMessage="Table PARAMETER_CONFIG already exists. Skipping creation of the table...">
			<not>
				<tableExists tableName="PARAMETER_CONFIG" />
			</not>
		</preConditions>
		<createTable tableName="PARAMETER_CONFIG">
			<column autoIncrement="true" name="ID" type="BIGINT">
				<constraints nullable="false" primaryKey="true" />
			</column>
			<column name="VERSION" type="INT" />
			<column name="PARAMETER_NAME" type="VARCHAR(255)" />
			<column name="PARAMETER_VALUE" type="VARCHAR(255)" />
			<column name="KEY_CHANNEL_ACQUISITION_CONFIG" type="BIGINT" />
			<column name="KEY_HARDWARE_ACQUISITION_CONFIG" type="BIGINT" />
		</createTable>
	</changeSet>
	<changeSet author="root (generated)" id="1343314492758-14">
		<preConditions onFail="MARK_RAN"
			onFailMessage="Table PHYSICS_VAL already exists. Skipping creation of the table...">
			<not>
				<tableExists tableName="PHYSICS_VAL" />
			</not>
		</preConditions>
		<createTable tableName="PHYSICS_VAL">
			<column name="VALUE_TYPE" type="VARCHAR(31)">
				<constraints nullable="false" />
			</column>
			<column autoIncrement="true" name="ID" type="BIGINT">
				<constraints nullable="false" primaryKey="true" />
			</column>
			<column name="VERSION" type="INT" />
			<column name="INT_VALUE" type="INT" />
			<column name="LONG_VALUE" type="BIGINT" />
			<column name="DATA" type="TINYBLOB" />
			<column name="MIMETYPE" type="VARCHAR(255)" />
			<column name="DOUBLE_VALUE" type="DOUBLE" />
			<column name="FLOAT_VALUE" type="FLOAT" />
			<column name="BOOLEAN_VALUE" type="BIT" />
			<column name="SHORT_VAL" type="SMALLINT" />
			<column name="BYTE_VALUE" type="TINYINT" />
		</createTable>
	</changeSet>
	<changeSet author="root (generated)" id="1343314492758-15">
		<preConditions onFail="MARK_RAN"
			onFailMessage="Table PRINCIPAL already exists. Skipping creation of the table...">
			<not>
				<tableExists tableName="PRINCIPAL" />
			</not>
		</preConditions>
		<createTable tableName="PRINCIPAL">
			<column name="INSTANCE_TYPE" type="VARCHAR(31)">
				<constraints nullable="false" />
			</column>
			<column autoIncrement="true" name="ID" type="BIGINT">
				<constraints nullable="false" primaryKey="true" />
			</column>
			<column name="VERSION" type="INT" />
			<column name="USERNAME" type="VARCHAR(255)" />
			<column name="NAME" type="VARCHAR(255)" />
			<column name="KEY_SUBJECT" type="BIGINT" />
		</createTable>
	</changeSet>
	<changeSet author="root (generated)" id="1343314492758-16">
		<preConditions onFail="MARK_RAN"
			onFailMessage="Table PRINCIPALS_ASSOCIATION already exists. Skipping creation of the table...">
			<not>
				<tableExists tableName="PRINCIPALS_ASSOCIATION" />
			</not>
		</preConditions>
		<createTable tableName="PRINCIPALS_ASSOCIATION">
			<column name="KEY_PARENT" type="BIGINT">
				<constraints nullable="false" />
			</column>
			<column name="KEY_CHILD" type="BIGINT">
				<constraints nullable="false" />
			</column>
		</createTable>
	</changeSet>
	<changeSet author="root (generated)" id="1343314492758-17">
		<preConditions onFail="MARK_RAN"
			onFailMessage="Table RESERVATION already exists. Skipping creation of the table...">
			<not>
				<tableExists tableName="RESERVATION" />
			</not>
		</preConditions>
		<createTable tableName="RESERVATION">
			<column autoIncrement="true" name="ID" type="BIGINT">
				<constraints nullable="false" primaryKey="true" />
			</column>
			<column name="VERSION" type="INT" />
			<column name="IS_ALL_DAY" type="BIT" />
			<column name="DOMAIN" type="VARCHAR(255)">
				<constraints nullable="false" />
			</column>
			<column name="END_DATE" type="DATETIME" />
			<column name="RESERVATION_ID" type="VARCHAR(255)" />
			<column name="START_DATE" type="DATETIME" />
			<column name="TITLE" type="VARCHAR(255)" />
			<column name="KEY_EXPERIMENT" type="BIGINT" />
			<column name="KEY_GROUP" type="BIGINT">
				<constraints nullable="false" />
			</column>
			<column name="KEY_USER" type="BIGINT">
				<constraints nullable="false" />
			</column>
		</createTable>
	</changeSet>
	<changeSet author="root (generated)" id="1343314492758-18">
		<preConditions onFail="MARK_RAN"
			onFailMessage="Table SAMPLES_PACKET_BLOB already exists. Skipping creation of the table...">
			<not>
				<tableExists tableName="SAMPLES_PACKET_BLOB" />
			</not>
		</preConditions>
		<createTable tableName="SAMPLES_PACKET_BLOB">
			<column autoIncrement="true" name="ID" type="BIGINT">
				<constraints nullable="false" primaryKey="true" />
			</column>
			<column name="VERSION" type="INT" />
			<column name="SAMPLES_PACKET_MATRIX_BLOB" type="LONGBLOB" />
		</createTable>
	</changeSet>
	<changeSet author="root (generated)" id="1343314492758-19">
		<preConditions onFail="MARK_RAN"
			onFailMessage="Table SCALE already exists. Skipping creation of the table...">
			<not>
				<tableExists tableName="SCALE" />
			</not>
		</preConditions>
		<createTable tableName="SCALE">
			<column autoIncrement="true" name="ID" type="BIGINT">
				<constraints nullable="false" primaryKey="true" />
			</column>
			<column name="VERSION" type="INT" />
			<column name="APPLIED_MULTIPLIER" type="VARCHAR(255)" />
			<column name="PHYSICS_UNIT_NAME" type="VARCHAR(255)" />
			<column name="PHYSICS_UNIT_SYMBOL" type="VARCHAR(255)" />
			<column name="SCALE_LABEL" type="VARCHAR(255)" />
			<column name="KEY_PHYSICS_VAL_DEFAULTERROR" type="BIGINT" />
			<column name="KEY_PHYSICS_VAL_MAXVALUE" type="BIGINT" />
			<column name="KEY_PHYSICS_VAL_MINVALUE" type="BIGINT" />
			<column name="KEY_PHYSICS_VAL_STEP" type="BIGINT" />
		</createTable>
	</changeSet>
	<changeSet author="root (generated)" id="1343314492758-20">
		<preConditions onFail="MARK_RAN"
			onFailMessage="Table SUBJECT already exists. Skipping creation of the table...">
			<not>
				<tableExists tableName="SUBJECT" />
			</not>
		</preConditions>
		<createTable tableName="SUBJECT">
			<column name="DTYPE" type="VARCHAR(31)">
				<constraints nullable="false" />
			</column>
			<column autoIncrement="true" name="ID" type="BIGINT">
				<constraints nullable="false" primaryKey="true" />
			</column>
			<column name="VERSION" type="INT" />
			<column name="EMAIL" type="VARCHAR(255)" />
			<column name="IS_MAIN" type="BIT" />
			<column name="TYPE" type="VARCHAR(255)" />
			<column name="FIRST_NAME" type="VARCHAR(255)">
				<constraints nullable="false" />
			</column>
			<column name="LAST_NAME" type="VARCHAR(255)">
				<constraints nullable="false" />
			</column>
		</createTable>
	</changeSet>
	<changeSet author="root (generated)" id="1343314492758-21">
		<preConditions onFail="MARK_RAN"
			onFailMessage="Table FKE74E55C33AFC7CA6 already exists. Skipping creation of the foreign key constraint...">
			<not>
				<foreignKeyConstraintExists
					foreignKeyName="FKE74E55C33AFC7CA6" />
			</not>
		</preConditions>
		<addForeignKeyConstraint baseColumnNames="KEY_AUDITED"
			baseTableName="AUDIT_OPERATION" baseTableSchemaName="allocation"
			constraintName="FKE74E55C33AFC7CA6" deferrable="false"
			initiallyDeferred="false" onDelete="NO ACTION" onUpdate="NO ACTION"
			referencedColumnNames="ID" referencedTableName="AUDITED_OBJECT"
			referencedTableSchemaName="allocation" referencesUniqueColumn="false" />
	</changeSet>
	<changeSet author="root (generated)" id="1343314492758-22">
		<preConditions onFail="MARK_RAN"
			onFailMessage="Table FKE74E55C3EC7DC58F already exists. Skipping creation of the foreign key constraint...">
			<not>
				<foreignKeyConstraintExists
					foreignKeyName="FKE74E55C3EC7DC58F" />
			</not>
		</preConditions>
		<addForeignKeyConstraint baseColumnNames="KEY_AUDITOR"
			baseTableName="AUDIT_OPERATION" baseTableSchemaName="allocation"
			constraintName="FKE74E55C3EC7DC58F" deferrable="false"
			initiallyDeferred="false" onDelete="NO ACTION" onUpdate="NO ACTION"
			referencedColumnNames="ID" referencedTableName="AUDITOR"
			referencedTableSchemaName="allocation" referencesUniqueColumn="false" />
	</changeSet>
	<changeSet author="root (generated)" id="1343314492758-23">
		<preConditions onFail="MARK_RAN"
			onFailMessage="Table FK34D98617963CA654 already exists. Skipping creation of the foreign key constraint...">
			<not>
				<foreignKeyConstraintExists
					foreignKeyName="FK34D98617963CA654" />
			</not>
		</preConditions>
		<addForeignKeyConstraint baseColumnNames="KEY_HARDWARE_ACQUISITION_CONFIG"
			baseTableName="CHANNEL_AQUISITION_CONFIG" baseTableSchemaName="allocation"
			constraintName="FK34D98617963CA654" deferrable="false"
			initiallyDeferred="false" onDelete="NO ACTION" onUpdate="NO ACTION"
			referencedColumnNames="ID" referencedTableName="HARDWARE_ACQUISITION_CONFIG"
			referencedTableSchemaName="allocation" referencesUniqueColumn="false" />
	</changeSet>
	<changeSet author="root (generated)" id="1343314492758-24">
		<preConditions onFail="MARK_RAN"
			onFailMessage="ForeignKeyConstraint FK34D98617D3EF5DD6 already exists. Skipping creation of the foreign key constraint...">
			<not>
				<foreignKeyConstraintExists
					foreignKeyName="FK34D98617D3EF5DD6" />
			</not>
		</preConditions>
		<addForeignKeyConstraint baseColumnNames="KEY_SCALE"
			baseTableName="CHANNEL_AQUISITION_CONFIG" baseTableSchemaName="allocation"
			constraintName="FK34D98617D3EF5DD6" deferrable="false"
			initiallyDeferred="false" onDelete="NO ACTION" onUpdate="NO ACTION"
			referencedColumnNames="ID" referencedTableName="SCALE"
			referencedTableSchemaName="allocation" referencesUniqueColumn="false" />
	</changeSet>
	<changeSet author="root (generated)" id="1343314492758-25">
		<preConditions onFail="MARK_RAN"
			onFailMessage="ForeignKeyConstraint FK28D00887963CA654 already exists. Skipping creation of the foreign key constraint...">
			<not>
				<foreignKeyConstraintExists
					foreignKeyName="FK28D00887963CA654" />
			</not>
		</preConditions>
		<addForeignKeyConstraint baseColumnNames="KEY_HARDWARE_ACQUISITION_CONFIG"
			baseTableName="DATA_PRODUCER" baseTableSchemaName="allocation"
			constraintName="FK28D00887963CA654" deferrable="false"
			initiallyDeferred="false" onDelete="NO ACTION" onUpdate="NO ACTION"
			referencedColumnNames="ID" referencedTableName="HARDWARE_ACQUISITION_CONFIG"
			referencedTableSchemaName="allocation" referencesUniqueColumn="false" />
	</changeSet>
	<changeSet author="root (generated)" id="1343314492758-26">
		<preConditions onFail="MARK_RAN"
			onFailMessage="ForeignKeyConstraint FK28D00887A1214B2E already exists. Skipping creation of the foreign key constraint...">
			<not>
				<foreignKeyConstraintExists
					foreignKeyName="FK28D00887A1214B2E" />
			</not>
		</preConditions>
		<addForeignKeyConstraint baseColumnNames="KEY_SAMPLES_PACKET_BLOB"
			baseTableName="DATA_PRODUCER" baseTableSchemaName="allocation"
			constraintName="FK28D00887A1214B2E" deferrable="false"
			initiallyDeferred="false" onDelete="NO ACTION" onUpdate="NO ACTION"
			referencedColumnNames="ID" referencedTableName="SAMPLES_PACKET_BLOB"
			referencedTableSchemaName="allocation" referencesUniqueColumn="false" />
	</changeSet>
	<changeSet author="root (generated)" id="1343314492758-27">
		<preConditions onFail="MARK_RAN"
			onFailMessage="ForeignKeyConstraint FK17D3C7FDDA4D64 already exists. Skipping creation of the foreign key constraint...">
			<not>
				<foreignKeyConstraintExists
					foreignKeyName="FK17D3C7FDDA4D64" />
			</not>
		</preConditions>
		<addForeignKeyConstraint baseColumnNames="KEY_LABORATORY"
			baseTableName="EXPERIMENT" baseTableSchemaName="allocation"
			constraintName="FK17D3C7FDDA4D64" deferrable="false"
			initiallyDeferred="false" onDelete="NO ACTION" onUpdate="NO ACTION"
			referencedColumnNames="ID" referencedTableName="LABORATORY"
			referencedTableSchemaName="allocation" referencesUniqueColumn="false" />
	</changeSet>
	<changeSet author="root (generated)" id="1343314492758-28">
		<preConditions onFail="MARK_RAN"
			onFailMessage="ForeignKeyConstraint FK9682266E7302AC2A already exists. Skipping creation of the foreign key constraint...">
			<not>
				<foreignKeyConstraintExists
					foreignKeyName="FK9682266E7302AC2A" />
			</not>
		</preConditions>
		<addForeignKeyConstraint baseColumnNames="KEY_USER"
			baseTableName="IDENTIFICATION" baseTableSchemaName="allocation"
			constraintName="FK9682266E7302AC2A" deferrable="false"
			initiallyDeferred="false" onDelete="NO ACTION" onUpdate="NO ACTION"
			referencedColumnNames="ID" referencedTableName="PRINCIPAL"
			referencedTableSchemaName="allocation" referencesUniqueColumn="false" />
	</changeSet>
	<changeSet author="root (generated)" id="1343314492758-29">
		<preConditions onFail="MARK_RAN"
			onFailMessage="ForeignKeyConstraint FK259B54B83BBD80DA already exists. Skipping creation of the foreign key constraint...">
			<not>
				<foreignKeyConstraintExists
					foreignKeyName="FK259B54B83BBD80DA" />
			</not>
		</preConditions>
		<addForeignKeyConstraint baseColumnNames="KEY_CHANNEL_ACQUISITION_CONFIG"
			baseTableName="PARAMETER_CONFIG" baseTableSchemaName="allocation"
			constraintName="FK259B54B83BBD80DA" deferrable="false"
			initiallyDeferred="false" onDelete="NO ACTION" onUpdate="NO ACTION"
			referencedColumnNames="ID" referencedTableName="CHANNEL_AQUISITION_CONFIG"
			referencedTableSchemaName="allocation" referencesUniqueColumn="false" />
	</changeSet>
	<changeSet author="root (generated)" id="1343314492758-30">
		<preConditions onFail="MARK_RAN"
			onFailMessage="ForeignKeyConstraint FK259B54B8963CA654 already exists. Skipping creation of the foreign key constraint...">
			<not>
				<foreignKeyConstraintExists
					foreignKeyName="FK259B54B8963CA654" />
			</not>
		</preConditions>
		<addForeignKeyConstraint baseColumnNames="KEY_HARDWARE_ACQUISITION_CONFIG"
			baseTableName="PARAMETER_CONFIG" baseTableSchemaName="allocation"
			constraintName="FK259B54B8963CA654" deferrable="false"
			initiallyDeferred="false" onDelete="NO ACTION" onUpdate="NO ACTION"
			referencedColumnNames="ID" referencedTableName="HARDWARE_ACQUISITION_CONFIG"
			referencedTableSchemaName="allocation" referencesUniqueColumn="false" />
	</changeSet>
	<changeSet author="root (generated)" id="1343314492758-31">
		<preConditions onFail="MARK_RAN"
			onFailMessage="ForeignKeyConstraint FK3A16800E16E29D44 already exists. Skipping creation of the foreign key constraint...">
			<not>
				<foreignKeyConstraintExists
					foreignKeyName="FK3A16800E16E29D44" />
			</not>
		</preConditions>
		<addForeignKeyConstraint baseColumnNames="KEY_SUBJECT"
			baseTableName="PRINCIPAL" baseTableSchemaName="allocation"
			constraintName="FK3A16800E16E29D44" deferrable="false"
			initiallyDeferred="false" onDelete="NO ACTION" onUpdate="NO ACTION"
			referencedColumnNames="ID" referencedTableName="SUBJECT"
			referencedTableSchemaName="allocation" referencesUniqueColumn="false" />
	</changeSet>
	<changeSet author="root (generated)" id="1343314492758-32">
		<preConditions onFail="MARK_RAN"
			onFailMessage="ForeignKeyConstraint FK431E712739AB5D36 already exists. Skipping creation of the foreign key constraint...">
			<not>
				<foreignKeyConstraintExists
					foreignKeyName="FK431E712739AB5D36" />
			</not>
		</preConditions>
		<addForeignKeyConstraint baseColumnNames="KEY_CHILD"
			baseTableName="PRINCIPALS_ASSOCIATION" baseTableSchemaName="allocation"
			constraintName="FK431E712739AB5D36" deferrable="false"
			initiallyDeferred="false" onDelete="NO ACTION" onUpdate="NO ACTION"
			referencedColumnNames="ID" referencedTableName="PRINCIPAL"
			referencedTableSchemaName="allocation" referencesUniqueColumn="false" />
	</changeSet>
	<changeSet author="root (generated)" id="1343314492758-33">
		<preConditions onFail="MARK_RAN"
			onFailMessage="ForeignKeyConstraint FK431E7127B5E33884 already exists. Skipping creation of the foreign key constraint...">
			<not>
				<foreignKeyConstraintExists
					foreignKeyName="FK431E7127B5E33884" />
			</not>
		</preConditions>
		<addForeignKeyConstraint baseColumnNames="KEY_PARENT"
			baseTableName="PRINCIPALS_ASSOCIATION" baseTableSchemaName="allocation"
			constraintName="FK431E7127B5E33884" deferrable="false"
			initiallyDeferred="false" onDelete="NO ACTION" onUpdate="NO ACTION"
			referencedColumnNames="ID" referencedTableName="PRINCIPAL"
			referencedTableSchemaName="allocation" referencesUniqueColumn="false" />
	</changeSet>
	<changeSet author="root (generated)" id="1343314492758-34">
		<preConditions onFail="MARK_RAN"
			onFailMessage="ForeignKeyConstraint FK2328D7AC84A125F8 already exists. Skipping creation of the foreign key constraint...">
			<not>
				<foreignKeyConstraintExists
					foreignKeyName="FK2328D7AC84A125F8" />
			</not>
		</preConditions>
		<addForeignKeyConstraint baseColumnNames="KEY_EXPERIMENT"
			baseTableName="RESERVATION" baseTableSchemaName="allocation"
			constraintName="FK2328D7AC84A125F8" deferrable="false"
			initiallyDeferred="false" onDelete="NO ACTION" onUpdate="NO ACTION"
			referencedColumnNames="ID" referencedTableName="EXPERIMENT"
			referencedTableSchemaName="allocation" referencesUniqueColumn="false" />
	</changeSet>
	<changeSet author="root (generated)" id="1343314492758-35">
		<preConditions onFail="MARK_RAN"
			onFailMessage="ForeignKeyConstraint FK2328D7ACEBC7AAEA already exists. Skipping creation of the foreign key constraint...">
			<not>
				<foreignKeyConstraintExists
					foreignKeyName="FK2328D7ACEBC7AAEA" />
			</not>
		</preConditions>
		<addForeignKeyConstraint baseColumnNames="KEY_GROUP"
			baseTableName="RESERVATION" baseTableSchemaName="allocation"
			constraintName="FK2328D7ACEBC7AAEA" deferrable="false"
			initiallyDeferred="false" onDelete="NO ACTION" onUpdate="NO ACTION"
			referencedColumnNames="ID" referencedTableName="PRINCIPAL"
			referencedTableSchemaName="allocation" referencesUniqueColumn="false" />
	</changeSet>
	<changeSet author="root (generated)" id="1343314492758-36">
		<preConditions onFail="MARK_RAN"
			onFailMessage="ForeignKeyConstraint FK2328D7AC7302AC2A already exists. Skipping creation of the foreign key constraint...">
			<not>
				<foreignKeyConstraintExists
					foreignKeyName="FK2328D7AC7302AC2A" />
			</not>
		</preConditions>
		<addForeignKeyConstraint baseColumnNames="KEY_USER"
			baseTableName="RESERVATION" baseTableSchemaName="allocation"
			constraintName="FK2328D7AC7302AC2A" deferrable="false"
			initiallyDeferred="false" onDelete="NO ACTION" onUpdate="NO ACTION"
			referencedColumnNames="ID" referencedTableName="PRINCIPAL"
			referencedTableSchemaName="allocation" referencesUniqueColumn="false" />
	</changeSet>
	<changeSet author="root (generated)" id="1343314492758-37">
		<preConditions onFail="MARK_RAN"
			onFailMessage="ForeignKeyConstraint FK4B1112A21E94515 already exists. Skipping creation of the foreign key constraint...">
			<not>
				<foreignKeyConstraintExists
					foreignKeyName="FK4B1112A21E94515" />
			</not>
		</preConditions>
		<addForeignKeyConstraint baseColumnNames="KEY_PHYSICS_VAL_DEFAULTERROR"
			baseTableName="SCALE" baseTableSchemaName="allocation" constraintName="FK4B1112A21E94515"
			deferrable="false" initiallyDeferred="false" onDelete="NO ACTION"
			onUpdate="NO ACTION" referencedColumnNames="ID" referencedTableName="PHYSICS_VAL"
			referencedTableSchemaName="allocation" referencesUniqueColumn="false" />
	</changeSet>
	<changeSet author="root (generated)" id="1343314492758-38">
		<preConditions onFail="MARK_RAN"
			onFailMessage="ForeignKeyConstraint FK4B1112A23133E3B already exists. Skipping creation of the foreign key constraint...">
			<not>
				<foreignKeyConstraintExists
					foreignKeyName="FK4B1112A23133E3B" />
			</not>
		</preConditions>
		<addForeignKeyConstraint baseColumnNames="KEY_PHYSICS_VAL_MAXVALUE"
			baseTableName="SCALE" baseTableSchemaName="allocation" constraintName="FK4B1112A23133E3B"
			deferrable="false" initiallyDeferred="false" onDelete="NO ACTION"
			onUpdate="NO ACTION" referencedColumnNames="ID" referencedTableName="PHYSICS_VAL"
			referencedTableSchemaName="allocation" referencesUniqueColumn="false" />
	</changeSet>
	<changeSet author="root (generated)" id="1343314492758-39">
		<preConditions onFail="MARK_RAN"
			onFailMessage="ForeignKeyConstraint FK4B1112AB934A20D already exists. Skipping creation of the foreign key constraint...">
			<not>
				<foreignKeyConstraintExists
					foreignKeyName="FK4B1112AB934A20D" />
			</not>
		</preConditions>
		<addForeignKeyConstraint baseColumnNames="KEY_PHYSICS_VAL_MINVALUE"
			baseTableName="SCALE" baseTableSchemaName="allocation" constraintName="FK4B1112AB934A20D"
			deferrable="false" initiallyDeferred="false" onDelete="NO ACTION"
			onUpdate="NO ACTION" referencedColumnNames="ID" referencedTableName="PHYSICS_VAL"
			referencedTableSchemaName="allocation" referencesUniqueColumn="false" />
	</changeSet>
	<changeSet author="root (generated)" id="1343314492758-40">
		<preConditions onFail="MARK_RAN"
			onFailMessage="ForeignKeyConstraint FK4B1112AE925257A already exists. Skipping creation of the foreign key constraint...">
			<not>
				<foreignKeyConstraintExists
					foreignKeyName="FK4B1112AE925257A" />
			</not>
		</preConditions>
		<addForeignKeyConstraint baseColumnNames="KEY_PHYSICS_VAL_STEP"
			baseTableName="SCALE" baseTableSchemaName="allocation" constraintName="FK4B1112AE925257A"
			deferrable="false" initiallyDeferred="false" onDelete="NO ACTION"
			onUpdate="NO ACTION" referencedColumnNames="ID" referencedTableName="PHYSICS_VAL"
			referencedTableSchemaName="allocation" referencesUniqueColumn="false" />
	</changeSet>
	<changeSet author="root (generated)" id="1343314492758-41">
		<preConditions onFail="MARK_RAN"
			onFailMessage="Index already exists. Skipping indexes generation...">
			<not>
				<indexExists tableName="DATA_PRODUCER" indexName="OID" />
			</not>
		</preConditions>
		<createIndex indexName="OID" tableName="DATA_PRODUCER"
			unique="true">
			<column name="OID" />
		</createIndex>
	</changeSet>
	<changeSet author="root (generated)" id="1343314492758-42">
		<preConditions onFail="MARK_RAN"
			onFailMessage="Index already exists. Skipping indexes generation...">
			<not>
				<indexExists tableName="EXPERIMENT" indexName="EXTERNAL_ID" />
			</not>
		</preConditions>
		<createIndex indexName="EXTERNAL_ID" tableName="EXPERIMENT"
			unique="true">
			<column name="EXTERNAL_ID" />
		</createIndex>
	</changeSet>
	<changeSet author="root (generated)" id="1343314492758-43">
		<preConditions onFail="MARK_RAN"
			onFailMessage="Index already exists. Skipping indexes generation...">
			<not>
				<indexExists tableName="LABORATORY" indexName="NAME" />
			</not>
		</preConditions>
		<createIndex indexName="NAME" tableName="LABORATORY"
			unique="true">
			<column name="NAME" />
		</createIndex>
	</changeSet>
	<changeSet author="root (generated)" id="1343314492758-44">
		<preConditions onFail="MARK_RAN"
			onFailMessage="Table already exists. Skipping indexes generation...">
			<not>
				<indexExists tableName="LOGIN_DOMAIN" indexName="NAME" />
			</not>
		</preConditions>
		<createIndex indexName="NAME" tableName="LOGIN_DOMAIN"
			unique="true">
			<column name="NAME" />
		</createIndex>
	</changeSet>
	<changeSet author="root (generated)" id="1343314492758-45">
		<preConditions onFail="MARK_RAN"
			onFailMessage="Index already exists. Skipping indexes generation...">
			<not>
				<indexExists tableName="PRINCIPAL" indexName="NAME" />
			</not>
		</preConditions>
		<createIndex indexName="NAME" tableName="PRINCIPAL"
			unique="true">
			<column name="NAME" />
		</createIndex>
	</changeSet>
	<changeSet author="root (generated)" id="1343314492758-46">
		<preConditions onFail="MARK_RAN"
			onFailMessage="Index already exists. Skipping indexes generation...">
			<not>
				<indexExists tableName="RESERVATION" indexName="RESERVATION_ID" />
			</not>
		</preConditions>
		<createIndex indexName="RESERVATION_ID" tableName="RESERVATION"
			unique="true">
			<column name="RESERVATION_ID" />
		</createIndex>
	</changeSet>
</databaseChangeLog>
